markdown_convert/__init__.py
markdown_convert/__main__.py
markdown_convert/code.css
markdown_convert/default.css
markdown_convert/modules/__init__.py
markdown_convert/modules/autoinstall.py
markdown_convert/modules/constants.py
markdown_convert/modules/convert.py
markdown_convert/modules/extras.py
markdown_convert/modules/overrides.py
markdown_convert/modules/resources.py
markdown_convert/modules/transform.py
markdown_convert/modules/utils.py
markdown_convert/modules/validate.py
markdown_convert-1.2.55.dist-info/METADATA
markdown_convert-1.2.55.dist-info/WHEEL
markdown_convert-1.2.55.dist-info/entry_points.txt
markdown_convert-1.2.55.dist-info/licenses/LICENSE
markdown_convert-1.2.55.dist-info/RECORD
