Metadata-Version: 2.4
Name: markdown_convert
Version: 1.2.55
Summary: Convert Markdown files to PDF from your command line.
Project-URL: homepage, https://github.com/Julynx/markdown_convert
Author-email: Julio Cabria <juliocabria@tutanota.com>
License: GPL-2.0-only
License-File: LICENSE
Classifier: License :: OSI Approved :: GNU General Public License v2 (GPLv2)
Classifier: Operating System :: OS Independent
Classifier: Programming Language :: Python :: 3
Requires-Python: <3.15,>=3.11
Requires-Dist: argsdict==1.0.0
Requires-Dist: beautifulsoup4>=4.14.3
Requires-Dist: install-playwright>=1.0.0
Requires-Dist: latex2mathml>=3.78.1
Requires-Dist: markdown2<3,>=2.4.13
Requires-Dist: playwright>=1.57.0
Requires-Dist: pygments<3,>=2.17.2
Requires-Dist: ruamel-yaml>=0.19.1
Requires-Dist: vl-convert-python>=1.9.0.post1
